README.md
setup.py
TransformerST.egg-info/PKG-INFO
TransformerST.egg-info/SOURCES.txt
TransformerST.egg-info/dependency_links.txt
TransformerST.egg-info/requires.txt
TransformerST.egg-info/top_level.txt
progress/__init__.py
progress/bar.py
progress/counter.py
progress/spinner.py