Metadata-Version: 2.1
Name: TransformerST
Version: 1.0.0
Summary: Innovative Super-Resolution in Spatial Transcriptomics- A Transformer Model Exploiting Histology Images and Spatial Gene Expression
Home-page: UNKNOWN
Author: Chris
Author-email: zhaocy.research@gmail.com
License: UNKNOWN
Platform: UNKNOWN
